pytest_ansible_playbook.py
pytest_ansible_playbook_runner-0.5.4.dist-info/AUTHORS
pytest_ansible_playbook_runner-0.5.4.dist-info/LICENSE
pytest_ansible_playbook_runner-0.5.4.dist-info/METADATA
pytest_ansible_playbook_runner-0.5.4.dist-info/WHEEL
pytest_ansible_playbook_runner-0.5.4.dist-info/entry_points.txt
pytest_ansible_playbook_runner-0.5.4.dist-info/top_level.txt
pytest_ansible_playbook_runner-0.5.4.dist-info/RECORD
