Metadata-Version: 2.1
Name: pytest-ansible-playbook-runner
Version: 0.5.4
Summary: Pytest fixture which runs given ansible playbook file.
Home-page: https://github.com/final-israel/pytest-ansible-playbook-runner
Author: Martin Bukatovič
Author-email: mbukatov@redhat.com
Maintainer: Pavel Rogovoy
Maintainer-email: pavelr@final.co.il
License: Apache 2.0
Platform: UNKNOWN
Classifier: Development Status :: 4 - Beta
Classifier: Framework :: Pytest
Classifier: Intended Audience :: Developers
Classifier: Topic :: Software Development :: Testing
Classifier: Programming Language :: Python
Classifier: Programming Language :: Python :: 3
Classifier: Programming Language :: Python :: 3.6
Classifier: Programming Language :: Python :: Implementation :: CPython
Classifier: Programming Language :: Python :: Implementation :: PyPy
Classifier: Operating System :: POSIX
Requires-Dist: playbook-runner (>=0.1.5)
Requires-Dist: pytest (>=3.1.0)
